seedCrypto/__init__.py
seedCrypto/const.py
seedCrypto/seed.py
seedCrypto/test.py
seedCrypto-1.1.0.dist-info/LICENSE
seedCrypto-1.1.0.dist-info/METADATA
seedCrypto-1.1.0.dist-info/WHEEL
seedCrypto-1.1.0.dist-info/top_level.txt
seedCrypto-1.1.0.dist-info/RECORD
