Metadata-Version: 2.1
Name: seedCrypto
Version: 1.1.0
Summary: kisa seed encryption and decryption
Home-page: https://github.com/blluv/seedCrypto
Author: blluv
Author-email: biluv@protonmail.com
License: MIT
License-File: LICENSE
